[
  { "year": 2026, "title": "Calibrated Explanations for Decision-Critical Foundation Models", "authors": "Aarya Mehta, Lin Chen, Sofia Alvarez", "venue": "ACM CHI", "type": "Conference", "featured": true, "doi": "https://doi.org/10.1145/0000000.0000001", "abstract": "A framework for measuring whether model explanations remain calibrated when decisions carry material consequences." },
  { "year": 2025, "title": "Auditing Multimodal Models Under Distribution Shift", "authors": "Aarya Mehta, Noor Khan", "venue": "NeurIPS", "type": "Conference", "featured": true, "doi": "https://doi.org/10.48550/arXiv.2501.00001", "abstract": "A systematic audit protocol for multimodal systems deployed beyond their original training environments." },
  { "year": 2025, "title": "Participatory Benchmarks for Public-Sector AI", "authors": "Maya Rao, Aarya Mehta, Elias Stein", "venue": "ACM FAccT", "type": "Conference", "featured": false, "doi": "https://doi.org/10.1145/0000000.0000002", "abstract": "Methods for building evaluation benchmarks with communities affected by public-sector automated decisions." },
  { "year": 2024, "title": "Uncertainty-Aware Forecasting for Regional Energy Grids", "authors": "Aarya Mehta, Daniel Okafor", "venue": "Nature Machine Intelligence", "type": "Journal", "featured": true, "doi": "https://doi.org/10.1038/s42256-024-00001", "abstract": "Probabilistic energy forecasting that communicates operational uncertainty to regional grid operators." },
  { "year": 2024, "title": "Data Statements for Climate Intelligence", "authors": "Aarya Mehta, Priya Nair, Ellen Wu", "venue": "Patterns", "type": "Journal", "featured": false, "doi": "https://doi.org/10.1016/j.patter.2024.000001", "abstract": "Documentation practices for the geographic, temporal, and institutional limits of climate datasets." },
  { "year": 2023, "title": "Fair Resource Allocation with Causal Representation Learning", "authors": "Aarya Mehta, Haruto Sato", "venue": "ICML", "type": "Conference", "featured": false, "doi": "https://doi.org/10.48550/arXiv.2301.00001", "abstract": "Causal representations for equitable allocation when historical outcomes encode structural disadvantage." }
]
